setup.cfg
setup.py
journal_api/__init__.py
journal_api/api.py
journal_api/exceptions.py
journal_api/types.py
journal_api.egg-info/PKG-INFO
journal_api.egg-info/SOURCES.txt
journal_api.egg-info/dependency_links.txt
journal_api.egg-info/not-zip-safe
journal_api.egg-info/top_level.txt