Metadata-Version: 2.1
Name: journal-api
Version: 1.3.8
Summary: Simple wrapper for edu.gounn.ru api
Home-page: UNKNOWN
Author: q_HelloWorld
Author-email: alexberxin@gmail.com
License: UNKNOWN
Platform: UNKNOWN
Requires: aiohttp
Requires: beautifulsoup4
